repodoc/__init__.py
repodoc/commands.py
repodoc/log.py
repodoc/prompt.py
repodoc/render.py
repodoc/writer.py
repodoc/templates/.gitattributes.j2
repodoc/templates/.gitignore.j2
repodoc/templates/.mailmap.j2
repodoc/templates/.readthedocs.yaml.j2
repodoc/templates/MANIFEST.in.j2
repodoc/templates/README.md.j2
repodoc/templates/setup.cfg.j2
repodoc/templates/setup.py.j2
repodoc/templates/.github/CODE_OF_CONDUCT.md.j2
repodoc/templates/.github/CONTRIBUTING.rst.j2
repodoc/templates/.github/PULL_REQUEST_TEMPLATE.md.j2
repodoc/templates/.github/SECURITY.md.j2
repodoc/templates/.github/SUPPORT.md.j2
repodoc/templates/.github/ISSUE_TEMPLATE/bug_report.md.j2
repodoc/templates/.github/ISSUE_TEMPLATE/config.yml.j2
repodoc/templates/.github/ISSUE_TEMPLATE/feature_request.md.j2
repodoc/templates/docs/Makefile.j2
repodoc/templates/docs/api.rst.j2
repodoc/templates/docs/conf.py.j2
repodoc/templates/docs/contents.rst.j2
repodoc/templates/docs/index.rst.j2
repodoc/templates/docs/make.bat.j2
repodoc/templates/docs/requirements.txt.j2
repodoc/templates/licences/AGPL.j2
repodoc/templates/licences/AGPLv3.j2
repodoc/templates/licences/APACHE.j2
repodoc/templates/licences/BEERWARE.j2
repodoc/templates/licences/BSDv2.j2
repodoc/templates/licences/BSDv3.j2
repodoc/templates/licences/BSDv4.j2
repodoc/templates/licences/FDL.j2
repodoc/templates/licences/GMGPL.j2
repodoc/templates/licences/GPLv1.j2
repodoc/templates/licences/GPLv2.j2
repodoc/templates/licences/GPLv3.j2
repodoc/templates/licences/ISC.j2
repodoc/templates/licences/LGPLv2.j2
repodoc/templates/licences/LGPLv3.j2
repodoc/templates/licences/MIT.j2
repodoc/templates/licences/MPLv2.j2
repodoc/templates/licences/WTFPL.j2
tekrepodoc-0.0.9.dist-info/LICENCE
tekrepodoc-0.0.9.dist-info/METADATA
tekrepodoc-0.0.9.dist-info/WHEEL
tekrepodoc-0.0.9.dist-info/entry_points.txt
tekrepodoc-0.0.9.dist-info/top_level.txt
tekrepodoc-0.0.9.dist-info/RECORD
