Metadata-Version: 2.1
Name: tekrepodoc
Version: 0.0.9
Summary: Utility Tool to Generate Common Project Files using sensible templates every one can agree on. Useful for Git Repositories, Supports Sphinx templates, Community Health Files, READMEs, pypi project configurations.
Home-page: https://github.com/TralahM/tekrepodoc
Author: Tralah M Brian
Author-email: musyoki.brian@tralahtek.com
License: GPLV3
Project-URL: Source, https://github.com/TralahM/tekrepodoc
Project-URL: Tracker, https://github.com/TralahM/tekrepodoc/issues
Project-URL: Documentation, https://github.com/TralahM/tekrepodoc
Classifier: Environment :: Web Environment
Classifier: Intended Audience :: Developers
Classifier: License :: OSI Approved :: GNU General Public License v3 (GPLv3)
Classifier: Operating System :: OS Independent
Classifier: Programming Language :: Python
Classifier: Programming Language :: Python :: 3
Classifier: Programming Language :: Python :: 3 :: Only
Classifier: Programming Language :: Python :: 3.6
Classifier: Programming Language :: Python :: 3.7
Classifier: Programming Language :: Python :: 3.8
Classifier: Topic :: Internet :: WWW/HTTP
Classifier: Topic :: Internet :: WWW/HTTP :: Dynamic Content
License-File: LICENCE
Requires-Dist: PyYaml
Requires-Dist: jinja2
Requires-Dist: shtab
Requires-Dist: jinja2-time
Requires-Dist: art
Provides-Extra: docs
Requires-Dist: sphinx ; extra == 'docs'
Requires-Dist: sphinx-automodapi ; extra == 'docs'
